narrativeparser/__init__.py
narrativeparser/main.py
narrativeparser/prompts.py
narrativeparser-2025.12.21083854.dist-info/METADATA
narrativeparser-2025.12.21083854.dist-info/WHEEL
narrativeparser-2025.12.21083854.dist-info/top_level.txt
narrativeparser-2025.12.21083854.dist-info/RECORD
