Metadata-Version: 2.4
Name: narrativeparser
Version: 2025.12.21083854
Summary: The package aims to help users analyze and understand nuanced narratives or statements by distinguishing between factual accounts and imaginative interpretations. Given a text input, it will process t
Author-email: narrativeparser <hi@eugene.plus>
License: MIT
Project-URL: Homepage, https://github.com/chigwell/narrativeparser
Requires-Python: >=3.9
Requires-Dist: langchain-llm7>=0.0.0
Requires-Dist: llmatch-messages>=0.0.0
Requires-Dist: langchain-core>=0.3.0
